odoo8_addon_account_type_multi_company-8.0.1.0.0-py2.7-nspkg.pth
odoo_addons/account_type_multi_company/__openerp__.py
odoo_addons/account_type_multi_company/__init__.py
odoo_addons/account_type_multi_company/README.rst
odoo_addons/account_type_multi_company/security/multi_company.xml
odoo_addons/account_type_multi_company/models/__init__.py
odoo_addons/account_type_multi_company/models/account_type.py
odoo_addons/account_type_multi_company/views/account_type.xml
odoo8_addon_account_type_multi_company-8.0.1.0.0.dist-info/top_level.txt
odoo8_addon_account_type_multi_company-8.0.1.0.0.dist-info/WHEEL
odoo8_addon_account_type_multi_company-8.0.1.0.0.dist-info/RECORD
odoo8_addon_account_type_multi_company-8.0.1.0.0.dist-info/metadata.json
odoo8_addon_account_type_multi_company-8.0.1.0.0.dist-info/DESCRIPTION.rst
odoo8_addon_account_type_multi_company-8.0.1.0.0.dist-info/METADATA
odoo8_addon_account_type_multi_company-8.0.1.0.0.dist-info/namespace_packages.txt
